memorybench/__init__.py
memorybench/__main__.py
memorybench/cli.py
memorybench/dataset_runner.py
memorybench/dataset_schema.py
memorybench/http_provider.py
memorybench/publish.py
memorybench/adapters/__init__.py
memorybench/adapters/base.py
memorybench/adapters/embedding_adapter.py
memorybench/adapters/graph_adapter.py
memorybench/adapters/hash_adapter.py
memorybench/adapters/ngram_adapter.py
memorybench/adapters/text_adapter.py
memorybench/examples/sample_dataset.jsonl
memory_harness-1.3.0.dist-info/METADATA
memory_harness-1.3.0.dist-info/WHEEL
memory_harness-1.3.0.dist-info/entry_points.txt
memory_harness-1.3.0.dist-info/top_level.txt
memory_harness-1.3.0.dist-info/RECORD
