Metadata-Version: 2.4
Name: memory-harness
Version: 1.3.0
Summary: Benchmark and validate AI memory systems
License-Expression: MIT
Classifier: Programming Language :: Python :: 3
Classifier: Programming Language :: Python :: 3 :: Only
Requires-Python: >=3.8
Requires-Dist: httpx>=0.24.0
Requires-Dist: numpy>=1.23
